pyRinexpro/__init__.py
pyRinexpro/client.py
pyRinexpro/logs.py
pyRinexpro/process.py
pyRinexpro/session.py
pyRinexpro/utils.py
pyRinexpro-0.1.3.dist-info/METADATA
pyRinexpro-0.1.3.dist-info/WHEEL
pyRinexpro-0.1.3.dist-info/top_level.txt
pyRinexpro-0.1.3.dist-info/RECORD
