Metadata-Version: 2.1
Name: pyRinexpro
Version: 0.1.3
Summary: Python client for the rinexpro API
Home-page: https://rinexpro.com/en/home/
Author: fbsolutions
Author-email: contact@rinexpro.com
License: UNKNOWN
Project-URL: Documentation, https://pyrinexpro.readthedocs.io/en/latest/
Project-URL: Source Code, https://github.com/fbsolutions/pyRinexpro
Project-URL: API, https://rinexpro.com/en/home/
Platform: UNKNOWN
Requires-Dist: simplekml
Requires-Dist: geojson
Requires-Dist: pandas
Requires-Dist: requests
